{
	"message":[
		{"project_accuntnumber":"010581","project_name":"睿丰12号"},
		{"project_accuntnumber":"010276","project_name":"睿丰16号"},
		{"project_accuntnumber":"010321","project_name":"睿丰17号"},
		{"project_accuntnumber":"010249","project_name":"睿丰18号"},
		{"project_accuntnumber":"010320","project_name":"睿丰19号"},
		{"project_accuntnumber":"010177","project_name":"睿丰1号"},
		{"project_accuntnumber":"010322","project_name":"睿丰22号"},
		{"project_accuntnumber":"010323","project_name":"睿丰24号"},
		{"project_accuntnumber":"010454","project_name":"睿丰25号"},
		{"project_accuntnumber":"010709","project_name":"睿丰26号"},
		{"project_accuntnumber":"010448","project_name":"睿丰27号"},
		{"project_accuntnumber":"010455","project_name":"睿丰28号"},
		{"project_accuntnumber":"010098","project_name":"睿丰2号"},
		{"project_accuntnumber":"010560","project_name":"睿丰31号"},
		{"project_accuntnumber":"010661","project_name":"睿丰32号"},
		{"project_accuntnumber":"010175","project_name":"睿丰3号"},
		{"project_accuntnumber":"010360","project_name":"睿丰5号"},
		{"project_accuntnumber":"010169","project_name":"睿丰6号"},
		{"project_accuntnumber":"010233","project_name":"睿丰7号"},
		{"project_accuntnumber":"010582","project_name":"睿丰9号"},
		{"project_accuntnumber":"001852","project_name":"睿信5期"},
		{"project_accuntnumber":"001459","project_name":"睿信三期"},
		{"project_accuntnumber":"001458","project_name":"睿信二期"},
		{"project_accuntnumber":"001464","project_name":"睿信四期"},
		{"project_accuntnumber":"001448","project_name":"睿信证券"},
		{"project_accuntnumber":"001189","project_name":"睿利2号"},
		{"project_accuntnumber":"008384","project_name":"睿宏1号"},
		{"project_accuntnumber":"010178","project_name":"睿宏3号"},
		{"project_accuntnumber":"010324","project_name":"睿宏4号"},
		{"project_accuntnumber":"008348","project_name":"睿智1号"},
		{"project_accuntnumber":"008376","project_name":"睿智2号"},
		{"project_accuntnumber":"008377","project_name":"睿智3号"},
		{"project_accuntnumber":"010097","project_name":"睿智6号"},
		{"project_accuntnumber":"010289","project_name":"睿熙1号"},
		{"project_accuntnumber":"001036","project_name":"睿益11号（证券）"},
		{"project_accuntnumber":"001048","project_name":"睿益12号（银行间）"},
		{"project_accuntnumber":"001046","project_name":"睿益14号（证券）"},
		{"project_accuntnumber":"001165","project_name":"睿益16号"},
		{"project_accuntnumber":"001017","project_name":"睿益5号（证券）"},
		{"project_accuntnumber":"001024","project_name":"睿益8号（证券）"},
		{"project_accuntnumber":"001515","project_name":"睿致11号"},
		{"project_accuntnumber":"001518","project_name":"睿致12号（证券）"},
		{"project_accuntnumber":"001542","project_name":"睿致13号"},
		{"project_accuntnumber":"001637","project_name":"睿致14号"},
		{"project_accuntnumber":"001526","project_name":"睿致16号"},
		{"project_accuntnumber":"001533","project_name":"睿致18号"},
		{"project_accuntnumber":"001529","project_name":"睿致19号"},
		{"project_accuntnumber":"001169","project_name":"睿致1号"},
		{"project_accuntnumber":"001557","project_name":"睿致22号"},
		{"project_accuntnumber":"001558","project_name":"睿致23号"},
		{"project_accuntnumber":"001560","project_name":"睿致25号"},
		{"project_accuntnumber":"001601","project_name":"睿致27号"},
		{"project_accuntnumber":"001600","project_name":"睿致28号"},
		{"project_accuntnumber":"001659","project_name":"睿致39号"},
		{"project_accuntnumber":"001666","project_name":"睿致42号"},
		{"project_accuntnumber":"001675","project_name":"睿致43号"},
		{"project_accuntnumber":"001688","project_name":"睿致59号"},
		{"project_accuntnumber":"001194","project_name":"睿致5号"},
		{"project_accuntnumber":"001689","project_name":"睿致60号"},
		{"project_accuntnumber":"010277","project_name":"睿致66号"},
		{"project_accuntnumber":"010465","project_name":"睿致68号"},
		{"project_accuntnumber":"010331","project_name":"睿致70号"},
		{"project_accuntnumber":"010450","project_name":"睿致77号"},
		{"project_accuntnumber":"001197","project_name":"睿致7号"},
		{"project_accuntnumber":"010484","project_name":"睿致80号"},
		{"project_accuntnumber":"010485","project_name":"睿致84号"},
		{"project_accuntnumber":"010555","project_name":"睿致85号"},
		{"project_accuntnumber":"010556","project_name":"睿致86号"},
		{"project_accuntnumber":"010278","project_name":"睿致88号"},
		{"project_accuntnumber":"001513","project_name":"睿致9号"},
		{"project_accuntnumber":"080013","project_name":"睿赢精选C类3期"},
		{"project_accuntnumber":"010164","project_name":"睿际单一信托"},
		{"project_accuntnumber":"010028","project_name":"神州牧12号"},
		{"project_accuntnumber":"010029","project_name":"神州牧13号"},
		{"project_accuntnumber":"010030","project_name":"神州牧14号"},
		{"project_accuntnumber":"008360","project_name":"神州牧赤兔1号"},
		{"project_accuntnumber":"010011","project_name":"神雾可交债1期"},
		{"project_accuntnumber":"001861","project_name":"福麟15号（富安达安晟1期）"},
		{"project_accuntnumber":"001855","project_name":"福麟3号（智诚4期）"},
		{"project_accuntnumber":"001854","project_name":"福麟5号（智诚5期）"},
		{"project_accuntnumber":"010161","project_name":"禾对冲一号"},
		{"project_accuntnumber":"010463","project_name":"私募证券基金34号（悟空）熵控量化"},
		{"project_accuntnumber":"010583","project_name":"私募证券基金46号（盈峰）盈泉1期"},
		{"project_accuntnumber":"001552","project_name":"笃道1期"},
		{"project_accuntnumber":"010055","project_name":"索菱股份员工持股"},
		{"project_accuntnumber":"010499","project_name":"紫荆花集合"},
		{"project_accuntnumber":"001506","project_name":"紫金港1号"},
		{"project_accuntnumber":"008677","project_name":"红岭量化精选"},
		{"project_accuntnumber":"008740","project_name":"红岭量化精选3期"},
		{"project_accuntnumber":"008741","project_name":"红岭量化精选4期"},
		{"project_accuntnumber":"001489","project_name":"美联融通"},
		{"project_accuntnumber":"008420","project_name":"聚恒1期"},
		{"project_accuntnumber":"008066","project_name":"聚瑞1号"},
		{"project_accuntnumber":"010136","project_name":"蚂蚁1号"},
		{"project_accuntnumber":"010137","project_name":"蚂蚁2号"},
		{"project_accuntnumber":"010411","project_name":"融和"},
		{"project_accuntnumber":"T00429","project_name":"融通资本悦众1号资管"},
		{"project_accuntnumber":"T00660","project_name":"融通资本理成新策略1期资产管理计划"},
		{"project_accuntnumber":"008409","project_name":"衍航2号"},
		{"project_accuntnumber":"001144","project_name":"裕晋5期"},
		{"project_accuntnumber":"T00724","project_name":"西南证券钧安1号集合资产管理计划"},
		{"project_accuntnumber":"001037","project_name":"西藏隆源对冲1号"},
		{"project_accuntnumber":"010376","project_name":"观富建享"},
		{"project_accuntnumber":"010475","project_name":"证信1号"},
		{"project_accuntnumber":"010225","project_name":"诚奇对冲尊享A期"},
		{"project_accuntnumber":"010226","project_name":"诚奇对冲尊享B期"},
		{"project_accuntnumber":"010227","project_name":"诚奇对冲尊享C期"},
		{"project_accuntnumber":"010228","project_name":"诚奇对冲尊享D期"},
		{"project_accuntnumber":"010229","project_name":"诚奇对冲尊享E期"},
		{"project_accuntnumber":"010330","project_name":"诚奇对冲尊享F期"},
		{"project_accuntnumber":"080009","project_name":"诚奇对冲私募基金"},
		{"project_accuntnumber":"010224","project_name":"诚奇对冲集合信托"},
		{"project_accuntnumber":"010059","project_name":"诚朴恒远1号"},
		{"project_accuntnumber":"008389","project_name":"诚盈1期"},
		{"project_accuntnumber":"T00056","project_name":"财通基金-玉泉博道1号资产管理计划"},
		{"project_accuntnumber":"T00658","project_name":"财通基金辉耀1号资管计划"},
		{"project_accuntnumber":"010532","project_name":"贵人鸟1号"},
		{"project_accuntnumber":"009330","project_name":"赢通14号"},
		{"project_accuntnumber":"001155","project_name":"赤子之心价值"},
		{"project_accuntnumber":"001545","project_name":"赤子之心单一"},
		{"project_accuntnumber":"001166","project_name":"赤子之心成长"},
		{"project_accuntnumber":"001347","project_name":"赤子之心成长丰收系列之A期"},
		{"project_accuntnumber":"001348","project_name":"赤子之心成长丰收系列之B期"},
		{"project_accuntnumber":"001349","project_name":"赤子之心成长丰收系列之C期"},
		{"project_accuntnumber":"001350","project_name":"赤子之心成长丰收系列之D期"},
		{"project_accuntnumber":"001393","project_name":"赤子之心成长丰登系列之A期"},
		{"project_accuntnumber":"001394","project_name":"赤子之心成长丰登系列之B期"},
		{"project_accuntnumber":"001395","project_name":"赤子之心成长丰登系列之C期"},
		{"project_accuntnumber":"001396","project_name":"赤子之心成长丰登系列之D期"},
		{"project_accuntnumber":"001548","project_name":"赤子之心招商单一"},
		{"project_accuntnumber":"010543","project_name":"运晟16号"},
		{"project_accuntnumber":"008081","project_name":"运晟3号"},
		{"project_accuntnumber":"010516","project_name":"运晟4号"},
		{"project_accuntnumber":"010622","project_name":"远望角容远3期"},
		{"project_accuntnumber":"001756","project_name":"重阳1期"},
		{"project_accuntnumber":"001762","project_name":"重阳2期"},
		{"project_accuntnumber":"001836","project_name":"重阳3期"},
		{"project_accuntnumber":"001752","project_name":"重阳6期"},
		{"project_accuntnumber":"001893","project_name":"重阳7期"},
		{"project_accuntnumber":"001215","project_name":"重阳尊享A期"},
		{"project_accuntnumber":"001216","project_name":"重阳尊享B期"},
		{"project_accuntnumber":"001217","project_name":"重阳尊享C期"},
		{"project_accuntnumber":"001218","project_name":"重阳尊享D期"},
		{"project_accuntnumber":"001219","project_name":"重阳尊享E期"},
		{"project_accuntnumber":"001238","project_name":"重阳尊享F期"},
		{"project_accuntnumber":"001239","project_name":"重阳尊享G期"},
		{"project_accuntnumber":"001240","project_name":"重阳尊享H期"},
		{"project_accuntnumber":"001241","project_name":"重阳尊享I期"},
		{"project_accuntnumber":"001242","project_name":"重阳尊享J期"},
		{"project_accuntnumber":"001337","project_name":"重阳尊享K期"},
		{"project_accuntnumber":"001338","project_name":"重阳尊享L期"},
		{"project_accuntnumber":"001339","project_name":"重阳尊享M期"},
		{"project_accuntnumber":"001340","project_name":"重阳尊享N期"},
		{"project_accuntnumber":"008012","project_name":"重阳稳健成长"},
		{"project_accuntnumber":"008707","project_name":"重阳稳健成长尊享A期"},
		{"project_accuntnumber":"008708","project_name":"重阳稳健成长尊享B期"},
		{"project_accuntnumber":"008709","project_name":"重阳稳健成长尊享C期"},
		{"project_accuntnumber":"008710","project_name":"重阳稳健成长尊享D期"},
		{"project_accuntnumber":"008711","project_name":"重阳稳健成长尊享E期"},
		{"project_accuntnumber":"008712","project_name":"重阳稳健成长尊享F期"},
		{"project_accuntnumber":"008713","project_name":"重阳稳健成长尊享G期"},
		{"project_accuntnumber":"008714","project_name":"重阳稳健成长尊享H期"},
		{"project_accuntnumber":"008715","project_name":"重阳稳健成长尊享I期"},
		{"project_accuntnumber":"008716","project_name":"重阳稳健成长尊享J期"},
		{"project_accuntnumber":"008717","project_name":"重阳稳健成长尊享K期"},
		{"project_accuntnumber":"008718","project_name":"重阳稳健成长尊享L期"},
		{"project_accuntnumber":"008727","project_name":"重阳稳健成长尊享U期"},
		{"project_accuntnumber":"001205","project_name":"重阳精选A号"},
		{"project_accuntnumber":"001207","project_name":"重阳精选B号"},
		{"project_accuntnumber":"010027","project_name":"量道多策略对冲目标缓冲集合信托"},
		{"project_accuntnumber":"080011","project_name":"量道多策略对冲私募证券投资基金"},
		{"project_accuntnumber":"001759","project_name":"金中和1期"},
		{"project_accuntnumber":"010168","project_name":"金戈量锐1号"},
		{"project_accuntnumber":"008075","project_name":"金海顺德2号"},
		{"project_accuntnumber":"010307","project_name":"金涌鑫悦香江一期"},
		{"project_accuntnumber":"001297","project_name":"金致一号"},
		{"project_accuntnumber":"001201","project_name":"金致三号"},
		{"project_accuntnumber":"001200","project_name":"金致二号"},
		{"project_accuntnumber":"001204","project_name":"金致五号"},
		{"project_accuntnumber":"001644","project_name":"鑫狮善渊守中"},
		{"project_accuntnumber":"008671","project_name":"鑫狮善渊守中A号"},
		{"project_accuntnumber":"008672","project_name":"鑫狮善渊守中B号"},
		{"project_accuntnumber":"008673","project_name":"鑫狮善渊守中C号"},
		{"project_accuntnumber":"008674","project_name":"鑫狮善渊守中D号"},
		{"project_accuntnumber":"008675","project_name":"鑫狮善渊守中E号"},
		{"project_accuntnumber":"001578","project_name":"鑫睿3号单一"},
		{"project_accuntnumber":"001579","project_name":"鑫睿4号单一"},
		{"project_accuntnumber":"001580","project_name":"鑫睿5号单一"},
		{"project_accuntnumber":"001581","project_name":"鑫睿6号单一"},
		{"project_accuntnumber":"001582","project_name":"鑫睿7号单一"},
		{"project_accuntnumber":"001583","project_name":"鑫睿8号单一"},
		{"project_accuntnumber":"008969","project_name":"鑫道债券12号"},
		{"project_accuntnumber":"008958","project_name":"鑫道债券1号"},
		{"project_accuntnumber":"008959","project_name":"鑫道债券2号"},
		{"project_accuntnumber":"008960","project_name":"鑫道债券6号"},
		{"project_accuntnumber":"008964","project_name":"鑫道债券7号"},
		{"project_accuntnumber":"008965","project_name":"鑫道债券8号"},
		{"project_accuntnumber":"008966","project_name":"鑫道债券9号"},
		{"project_accuntnumber":"008084","project_name":"银安1号"},
		{"project_accuntnumber":"010047","project_name":"银宏尊享1号"},
		{"project_accuntnumber":"010061","project_name":"银宏尊享2号"},
		{"project_accuntnumber":"010135","project_name":"银宏尊享3号"},
		{"project_accuntnumber":"001105","project_name":"银帆5期"},
		{"project_accuntnumber":"001106","project_name":"银帆6期"},
		{"project_accuntnumber":"001109","project_name":"银帆7期"},
		{"project_accuntnumber":"008387","project_name":"银河一期"},
		{"project_accuntnumber":"T00714","project_name":"银河盛汇睿丰1号集合资产管理计划"},
		{"project_accuntnumber":"001172","project_name":"锐进2期"},
		{"project_accuntnumber":"001173","project_name":"锐进3期"},
		{"project_accuntnumber":"001616","project_name":"锐进42期"},
		{"project_accuntnumber":"001528","project_name":"锦华1号"},
		{"project_accuntnumber":"008031","project_name":"锦华2号"},
		{"project_accuntnumber":"T00703","project_name":"长城金债稳盈增强5号集合资产管理计划"},
		{"project_accuntnumber":"001412","project_name":"长江稳健（亿龙中国）"},
		{"project_accuntnumber":"T00688","project_name":"长江资管招胜1号集合资产管理计划"},
		{"project_accuntnumber":"T00720","project_name":"长江资管睿丰1号集合资产管理计划"},
		{"project_accuntnumber":"001598","project_name":"长河优势3号"},
		{"project_accuntnumber":"008519","project_name":"长河优势精选B期"},
		{"project_accuntnumber":"008520","project_name":"长河优势精选C期"},
		{"project_accuntnumber":"010265","project_name":"长金银信宝1期"},
		{"project_accuntnumber":"008340","project_name":"长阳精选1号"},
		{"project_accuntnumber":"001525","project_name":"长青1期"},
		{"project_accuntnumber":"001039","project_name":"长青藤2期"},
		{"project_accuntnumber":"001358","project_name":"阳光宝1号"},
		{"project_accuntnumber":"001359","project_name":"阳光宝2号"},
		{"project_accuntnumber":"001389","project_name":"阳光宝3号"},
		{"project_accuntnumber":"008471","project_name":"阿尔丁一期单一"},
		{"project_accuntnumber":"008371","project_name":"雅利上善若水1号"},
		{"project_accuntnumber":"008372","project_name":"雅利厚德载物1号"},
		{"project_accuntnumber":"008373","project_name":"雅利行胜于言1号"},
		{"project_accuntnumber":"008444","project_name":"韬蕴2号"},
		{"project_accuntnumber":"008014","project_name":"顶秀雄楚"},
		{"project_accuntnumber":"008319","project_name":"领骥瑞森"},
		{"project_accuntnumber":"008357","project_name":"领骥瑞森2号"},
		{"project_accuntnumber":"008358","project_name":"领骥瑞森3号"},
		{"project_accuntnumber":"010566","project_name":"飞利信员工持股1期"},
		{"project_accuntnumber":"001646","project_name":"高信百诺价值成长"},
		{"project_accuntnumber":"008052","project_name":"高毅利伟朴实"},
		{"project_accuntnumber":"008742","project_name":"高毅利伟朴实精选A期"},
		{"project_accuntnumber":"010471","project_name":"高毅利伟策远7号"},
		{"project_accuntnumber":"010474","project_name":"高毅利伟臻实"},
		{"project_accuntnumber":"010479","project_name":"高毅国鹭精选"},
		{"project_accuntnumber":"010491","project_name":"高毅国鹭精选1期"},
		{"project_accuntnumber":"010492","project_name":"高毅国鹭精选2期"},
		{"project_accuntnumber":"010163","project_name":"鲁证汇泉万泰FOF2期"},
		{"project_accuntnumber":"010072","project_name":"鸿获1号"},
		{"project_accuntnumber":"001889","project_name":"鸿道4期"},
		{"project_accuntnumber":"010024","project_name":"鸿顺和1号"},
		{"project_accuntnumber":"T00661","project_name":"鹏华基金-玲珑1号定增资管计划 "},
		{"project_accuntnumber":"T00560","project_name":"鹏华资产凯撒增持1号资产管理计划"},
		{"project_accuntnumber":"T00598","project_name":"鹏华资产猛狮1号资产管理计划"},
		{"project_accuntnumber":"T00606","project_name":"鹏华资产皓熙定增1号资产管理计划"},
		{"project_accuntnumber":"008926","project_name":"鹏扬基金稳利10号"},
		{"project_accuntnumber":"008927","project_name":"鹏扬基金稳利11号"},
		{"project_accuntnumber":"008928","project_name":"鹏扬基金稳利12号"},
		{"project_accuntnumber":"008917","project_name":"鹏扬基金稳利1号"},
		{"project_accuntnumber":"008918","project_name":"鹏扬基金稳利2号"},
		{"project_accuntnumber":"008919","project_name":"鹏扬基金稳利3号"},
		{"project_accuntnumber":"008920","project_name":"鹏扬基金稳利4号"},
		{"project_accuntnumber":"008921","project_name":"鹏扬基金稳利5号"},
		{"project_accuntnumber":"008922","project_name":"鹏扬基金稳利6号"},
		{"project_accuntnumber":"008923","project_name":"鹏扬基金稳利7号"},
		{"project_accuntnumber":"008924","project_name":"鹏扬基金稳利8号"},
		{"project_accuntnumber":"008925","project_name":"鹏扬基金稳利9号"},
		{"project_accuntnumber":"001764","project_name":"麦达证券"},
		{"project_accuntnumber":"008499","project_name":"鼎益丰天河10号"},
		{"project_accuntnumber":"001550","project_name":"鼎睿博荟专享"},
		{"project_accuntnumber":"001535","project_name":"鼎睿博荟单一"},
		{"project_accuntnumber":"001128","project_name":"鼎萨3期"},
		{"project_accuntnumber":"001335","project_name":"鼎诺安锐101期"},
		{"project_accuntnumber":"001336","project_name":"鼎诺安锐102期"},
		{"project_accuntnumber":"001897","project_name":"龙信基金通1号（泽熙11期）"},
		{"project_accuntnumber":"001725","project_name":"龙票1期"},
		{"project_accuntnumber":"001716","project_name":"龙腾证券"}
	]
}